py.typed
orq_ai_sdk/__init__.py
orq_ai_sdk/_hooks/__init__.py
orq_ai_sdk/_hooks/global.py
orq_ai_sdk/_hooks/registration.py
orq_ai_sdk/_hooks/sdkhooks.py
orq_ai_sdk/_hooks/types.py
orq_ai_sdk/_version.py
orq_ai_sdk/basesdk.py
orq_ai_sdk/contacts.py
orq_ai_sdk/deployments_sdk.py
orq_ai_sdk/feedback.py
orq_ai_sdk/files.py
orq_ai_sdk/httpclient.py
orq_ai_sdk/metrics.py
orq_ai_sdk/models/__init__.py
orq_ai_sdk/models/apierror.py
orq_ai_sdk/models/createcontactop.py
orq_ai_sdk/models/createfeedbackop.py
orq_ai_sdk/models/createpromptop.py
orq_ai_sdk/models/createpromptsnippetop.py
orq_ai_sdk/models/deletepromptop.py
orq_ai_sdk/models/deletepromptsnippetop.py
orq_ai_sdk/models/deploymentcreatemetricop.py
orq_ai_sdk/models/deploymentgetconfigop.py
orq_ai_sdk/models/deploymentinvokeop.py
orq_ai_sdk/models/deployments.py
orq_ai_sdk/models/deploymentsop.py
orq_ai_sdk/models/deploymentstreamop.py
orq_ai_sdk/models/filedeleteop.py
orq_ai_sdk/models/filegetop.py
orq_ai_sdk/models/filelistop.py
orq_ai_sdk/models/fileuploadop.py
orq_ai_sdk/models/findonepromptsnippetop.py
orq_ai_sdk/models/getallpromptsop.py
orq_ai_sdk/models/getonepromptop.py
orq_ai_sdk/models/honoapierror.py
orq_ai_sdk/models/internal/__init__.py
orq_ai_sdk/models/internal/globals.py
orq_ai_sdk/models/remoteconfigsgetconfigop.py
orq_ai_sdk/models/security.py
orq_ai_sdk/models/updatepromptop.py
orq_ai_sdk/models/updatepromptsnippetop.py
orq_ai_sdk/prompts.py
orq_ai_sdk/promptsnippets.py
orq_ai_sdk/py.typed
orq_ai_sdk/remoteconfig.py
orq_ai_sdk/sdk.py
orq_ai_sdk/sdkconfiguration.py
orq_ai_sdk/types/__init__.py
orq_ai_sdk/types/basemodel.py
orq_ai_sdk/utils/__init__.py
orq_ai_sdk/utils/annotations.py
orq_ai_sdk/utils/enums.py
orq_ai_sdk/utils/eventstreaming.py
orq_ai_sdk/utils/forms.py
orq_ai_sdk/utils/headers.py
orq_ai_sdk/utils/logger.py
orq_ai_sdk/utils/metadata.py
orq_ai_sdk/utils/queryparams.py
orq_ai_sdk/utils/requestbodies.py
orq_ai_sdk/utils/retries.py
orq_ai_sdk/utils/security.py
orq_rc_global_parameters-3.0.11.dist-info/METADATA
orq_rc_global_parameters-3.0.11.dist-info/WHEEL
orq_rc_global_parameters-3.0.11.dist-info/RECORD
